pyfs_pay/__init__.py
pyfs_pay/pay.py
pyfs_pay-1.0.1.dist-info/METADATA
pyfs_pay-1.0.1.dist-info/WHEEL
pyfs_pay-1.0.1.dist-info/top_level.txt
pyfs_pay-1.0.1.dist-info/RECORD
